json_to_xml_cli/__init__.py
json_to_xml_cli/cli.py
json_to_xml_cli-0.1.0.dist-info/licenses/LICENSE
json_to_xml_cli-0.1.0.dist-info/METADATA
json_to_xml_cli-0.1.0.dist-info/WHEEL
json_to_xml_cli-0.1.0.dist-info/entry_points.txt
json_to_xml_cli-0.1.0.dist-info/top_level.txt
json_to_xml_cli-0.1.0.dist-info/RECORD
