Metadata-Version: 2.4
Name: json-to-xml-cli
Version: 0.1.0
Summary: CLI tool to convert JSON files into XML format.
Author: jsonviewertool
License: MIT
Project-URL: Homepage, https://jsonviewertool.com/json-to-xml
Project-URL: Repository, https://github.com/coderaviverma/json-viewer-tools
Keywords: json,cli,converter
Requires-Python: >=3.9
License-File: LICENSE
Dynamic: license-file
